{"objects": [{"name": "FIN10", "description": "[FIN10](https://attack.mitre.org/groups/G0051) is a financially motivated threat group that has targeted organizations in North America since at least 2013 through 2016. The group uses stolen data exfiltrated from victims to extort organizations. (Citation: FireEye FIN10 June 2017)", "created_by_ref": "identity--ae82a5e5-ec07-4863-ad88-6504b29f24e9", "type": "intrusion-set", "aliases": ["FIN10"], "external_references": [{"source_name": "mitre-attack", "url": "https://attack.mitre.org/groups/G0051", "external_id": "G0051"}, {"source_name": "FIN10", "description": "(Citation: FireEye FIN10 June 2017)"}, {"url": "https://www2.fireeye.com/rs/848-DID-242/images/rpt-fin10.pdf", "description": "FireEye iSIGHT Intelligence. (2017, June 16). FIN10: Anatomy of a Cyber Extortion Operation. Retrieved June 25, 2017.", "source_name": "FireEye FIN10 June 2017"}], "primary_motivation": "personal-gain", "x_mitre_version": "1.2", "spec_version": "2.1", "id": "intrusion-set--9150a284-d156-4547-bbac-9ad6a1eadf01", "created": "2021-05-12T13:10:34.716196Z", "modified": "2021-05-12T13:10:34.716196Z"}], "type": "bundle", "id": "bundle--63b97e98-cb44-4db5-bfc9-7d53af27d333"}